avocado_glib/__init__.py
avocado_framework_plugin_glib-82.2.dist-info/METADATA
avocado_framework_plugin_glib-82.2.dist-info/WHEEL
avocado_framework_plugin_glib-82.2.dist-info/entry_points.txt
avocado_framework_plugin_glib-82.2.dist-info/top_level.txt
avocado_framework_plugin_glib-82.2.dist-info/RECORD
