Metadata-Version: 2.1
Name: avocado-framework-plugin-glib
Version: 82.2
Summary: Avocado Plugin for Execution of GLib Test Framework tests
Home-page: http://avocado-framework.github.io/
Author: Avocado Developers
Author-email: avocado-devel@redhat.com
License: UNKNOWN
Platform: UNKNOWN
Requires-Dist: avocado-framework (==82.2)
